nltk_com_fsd/__init__.py
nltk_com_fsd/info.txt
nltk_com_fsd/main.py
nltk_com_fsd-0.1.2.dist-info/METADATA
nltk_com_fsd-0.1.2.dist-info/WHEEL
nltk_com_fsd-0.1.2.dist-info/top_level.txt
nltk_com_fsd-0.1.2.dist-info/RECORD
