Metadata-Version: 2.1
Name: nltk-com-fsd
Version: 0.1.2
Summary: Demo package with greet function and text file
Home-page: UNKNOWN
Author: Your Name
Author-email: you@example.com
License: UNKNOWN
Platform: UNKNOWN
Requires-Python: >=3.7
